cpp_ekitty_simulator.cp311-win_amd64.pyd
electrokitty/ElectroKitty_MCMC_sampler.py
electrokitty/ElectroKitty_base_class.py
electrokitty/ElectroKitty_loss_functions.py
electrokitty/ElectroKitty_optimization_controler.py
electrokitty/ElectroKitty_parser.py
electrokitty/ElectroKitty_simulator.py
electrokitty/__init__.py
electrokitty/optimization_routines.py
electrokitty/cpp_code/__init__.py
electrokitty-1.0.10.51.dist-info/LICENCE
electrokitty-1.0.10.51.dist-info/METADATA
electrokitty-1.0.10.51.dist-info/WHEEL
electrokitty-1.0.10.51.dist-info/top_level.txt
electrokitty-1.0.10.51.dist-info/RECORD
