Metadata-Version: 2.1
Name: electrokitty
Version: 1.0.10.51
Summary: A simulation and simple analysis tool for electrochemical data
Home-page: https://github.com/RedrumKid/ElectroKitty
Author: Ožbej Vodeb
Author-email: ozbej.vodeb@gmail.com
License: BSD
Requires-Python: >=3.7
License-File: LICENCE
Requires-Dist: numpy>=1.20.0
Requires-Dist: scipy>=1.11.3
Requires-Dist: matplotlib>=3.8.0
Requires-Dist: cma>=3.3.0
